setup.py
webassets_ng_annotate.py
webassets_ng_annotate.egg-info/PKG-INFO
webassets_ng_annotate.egg-info/SOURCES.txt
webassets_ng_annotate.egg-info/dependency_links.txt
webassets_ng_annotate.egg-info/requires.txt
webassets_ng_annotate.egg-info/top_level.txt