Metadata-Version: 1.1
Name: webassets-ng-annotate
Version: 0.0.1
Summary: Ng-annotate filter for webassets.
Home-page: https://github.com/imbolc/webassets_ng_annotate
Author: Imbolc
Author-email: imbolc@imbolc.name
License: ISC
Platform: UNKNOWN
Classifier: Development Status :: 4 - Beta
Classifier: Intended Audience :: Developers
Classifier: License :: OSI Approved :: ISC License (ISCL)
Classifier: Programming Language :: Python
Classifier: Programming Language :: Python :: 3
